opeth/__init__.py
opeth/circbuff.py
opeth/colldata.py
opeth/comm.py
opeth/gui.py
opeth/logsetup.py
opeth/openephys.py
opeth/pgext.py
opeth/spike_gui.py
opeth/version.py
opeth-0.1a1.dist-info/LICENSE
opeth-0.1a1.dist-info/METADATA
opeth-0.1a1.dist-info/WHEEL
opeth-0.1a1.dist-info/entry_points.txt
opeth-0.1a1.dist-info/top_level.txt
opeth-0.1a1.dist-info/RECORD
