Metadata-Version: 2.1
Name: opeth
Version: 0.1a1
Summary: Online Peri-Event Histogram for Open Ephys ZMQ plugin
Home-page: https://github.com/hangyabalazs/opeth
Author: Andras Szell
Author-email: szell.andris@gmail.com
License: UNKNOWN
Project-URL: Documentation, https://opeth.readthedocs.io/en/latest
Project-URL: Source, https://github.com/hangyabalazs/opeth
Platform: UNKNOWN
Classifier: Development Status :: 4 - Beta
Classifier: Programming Language :: Python :: 2.7
Classifier: Programming Language :: Python :: 3
Classifier: License :: OSI Approved :: GNU General Public License v3 or later (GPLv3+)
Classifier: Operating System :: OS Independent
Classifier: Intended Audience :: Science/Research
Requires-Dist: pyqtgraph
Requires-Dist: pyzmq
Requires-Dist: enum ; python_version < "3"
Requires-Dist: python-qt5 ; python_version < "3"
Requires-Dist: pyqt5 ; python_version >= "3"
